README.md
setup.py
bin/kle-view
kle/__init__.py
kle/kle.py
kle/version.py
kle.egg-info/PKG-INFO
kle.egg-info/SOURCES.txt
kle.egg-info/dependency_links.txt
kle.egg-info/not-zip-safe
kle.egg-info/requires.txt
kle.egg-info/top_level.txt