Metadata-Version: 1.0
Name: kle
Version: 0.0.5
Summary: Python library for parsing keyboard layout files from keyboard-layout-editor.com.
Home-page: http://github.com/ahtn/python-kle
Author: jem
Author-email: jem@seethis.link
License: MIT
Keywords: keyboard,keyboard-layout-editor
Platform: UNKNOWN
